mcpwire/__init__.py
mcpwire/client.py
mcpwire/exceptions.py
mcpwire/models.py
mcpwire/utils.py
mcpwire-0.5.1.dist-info/licenses/LICENSE
mcpwire-0.5.1.dist-info/METADATA
mcpwire-0.5.1.dist-info/WHEEL
mcpwire-0.5.1.dist-info/top_level.txt
mcpwire-0.5.1.dist-info/RECORD
