Metadata-Version: 2.4
Name: mcpwire
Version: 0.5.1
Summary: A Python client for the Model Context Protocol (MCP), using the official MCP library and langchain-mcp-adapters.
Author-email: Anukool Chaturvedi <chaturvedianukool@gmail.com>
License: # mcpwire/LICENSE
Project-URL: Homepage, https://github.com/anukchat/mcpwire
Project-URL: Repository, https://github.com/anukchat/mcpwire
Project-URL: Issues, https://github.com/anukchat/mcpwire/issues
Classifier: Programming Language :: Python :: 3
Classifier: Programming Language :: Python :: 3.10
Classifier: Programming Language :: Python :: 3.11
Classifier: Programming Language :: Python :: 3.12
Classifier: License :: OSI Approved :: MIT License
Classifier: Operating System :: OS Independent
Classifier: Intended Audience :: Developers
Classifier: Topic :: Communications
Classifier: Topic :: Software Development :: Libraries :: Python Modules
Classifier: Topic :: Scientific/Engineering :: Artificial Intelligence
Requires-Python: >=3.10
License-File: LICENSE
Requires-Dist: mcp>=1.6.0
Requires-Dist: langchain-mcp-adapters>=0.0.7
Requires-Dist: langchain-core>=0.3.36
Requires-Dist: pydantic>=2.0
Provides-Extra: dev
Requires-Dist: pytest>=7.0; extra == "dev"
Requires-Dist: pytest-asyncio>=0.23.0; extra == "dev"
Requires-Dist: requests-mock>=1.9; extra == "dev"
Requires-Dist: pytest-cov>=4.0; extra == "dev"
Requires-Dist: mock>=5.0.0; extra == "dev"
Requires-Dist: pytest-mock>=3.10.0; extra == "dev"
Requires-Dist: aioresponses>=0.7.4; extra == "dev"
Requires-Dist: langchain>=0.1.0; extra == "dev"
Requires-Dist: langchain_openai>=0.1.0; extra == "dev"
Requires-Dist: langgraph>=0.1.0; extra == "dev"
Dynamic: license-file
